trw_wrapper/__init__.py
trw_wrapper/trw_wrapper.py
trw_wrapper-0.1.0.dist-info/METADATA
trw_wrapper-0.1.0.dist-info/WHEEL
trw_wrapper-0.1.0.dist-info/top_level.txt
trw_wrapper-0.1.0.dist-info/RECORD
