Metadata-Version: 2.4
Name: trw-wrapper
Version: 0.1.0
Summary: Un wrapper simple para la API de TRW
Home-page: https://github.com/KirbyHacks/trw-wrapper
Author: ! rLøw
Author-email: i@rlow.lol
Classifier: Programming Language :: Python :: 3
Classifier: License :: OSI Approved :: MIT License
Classifier: Operating System :: OS Independent
Requires-Python: >=3.6
Requires-Dist: requests>=2.25.1
Dynamic: author
Dynamic: author-email
Dynamic: classifier
Dynamic: description
Dynamic: description-content-type
Dynamic: home-page
Dynamic: requires-dist
Dynamic: requires-python
Dynamic: summary
